golf_enterprise/__init__.py
golf_enterprise/factory.py
golf_enterprise/oauth_proxy.py
golf_mcp_enterprise-0.1.0.dist-info/METADATA
golf_mcp_enterprise-0.1.0.dist-info/WHEEL
golf_mcp_enterprise-0.1.0.dist-info/top_level.txt
golf_mcp_enterprise-0.1.0.dist-info/RECORD
