Metadata-Version: 2.4
Name: golf-mcp-enterprise
Version: 0.1.0
Summary: Enterprise OAuth proxy features for Golf MCP servers
Author-email: Antoni Gmitruk <antoni@golf.dev>
License: Commercial License - Contact sales@golf.dev
Project-URL: Homepage, https://golf.dev
Project-URL: Documentation, https://docs.golf.dev
Project-URL: Support, https://golf.dev
Classifier: Programming Language :: Python :: 3
Classifier: Operating System :: OS Independent
Classifier: Development Status :: 4 - Beta
Classifier: Intended Audience :: Developers
Classifier: Topic :: Software Development :: Libraries :: Python Modules
Classifier: Programming Language :: Python :: 3.8
Classifier: Programming Language :: Python :: 3.9
Classifier: Programming Language :: Python :: 3.10
Classifier: Programming Language :: Python :: 3.11
Classifier: Programming Language :: Python :: 3.12
Requires-Python: >=3.8
Requires-Dist: golf-mcp<0.3.0,>=0.2.1
Requires-Dist: fastmcp<3.0.0,>=2.11.0
Requires-Dist: pydantic>=2.11.0
Requires-Dist: httpx>=0.28.1
Requires-Dist: pyjwt>=2.0.0
Requires-Dist: cryptography>=3.0.0
Provides-Extra: dev
Requires-Dist: pytest>=7.4.0; extra == "dev"
Requires-Dist: pytest-asyncio>=0.23.0; extra == "dev"
Requires-Dist: pytest-cov>=4.1.0; extra == "dev"
Requires-Dist: ruff>=0.1.0; extra == "dev"
Requires-Dist: mypy>=1.6.0; extra == "dev"
Requires-Dist: pytest-mock>=3.14.0; extra == "dev"
Provides-Extra: cython
Requires-Dist: cython>=3.0.0; extra == "cython"
Requires-Dist: numpy>=1.21.0; extra == "cython"
